awesome_codename/__init__.py
awesome_codename/__main__.py
awesome_codename/data/__init__.py
awesome_codename/data/adjectives.txt
awesome_codename/data/nouns.txt
awesome_codename-1.0.0.dist-info/DESCRIPTION.rst
awesome_codename-1.0.0.dist-info/METADATA
awesome_codename-1.0.0.dist-info/RECORD
awesome_codename-1.0.0.dist-info/WHEEL
awesome_codename-1.0.0.dist-info/entry_points.txt
awesome_codename-1.0.0.dist-info/metadata.json
awesome_codename-1.0.0.dist-info/top_level.txt
