Metadata-Version: 2.0
Name: awesome-codename
Version: 1.0.0
Summary: Awesome Codename Generator
Home-page: https://github.com/rolando/awesome-codename
Author: Rolando (Max) Espinoza
Author-email: rolando@rmax.io
License: AGPL
Keywords: awesome-codename
Platform: UNKNOWN
Classifier: Development Status :: 4 - Beta
Classifier: Intended Audience :: Developers
Classifier: License :: OSI Approved :: GNU Affero General Public License v3
Classifier: Natural Language :: English
Classifier: Programming Language :: Python :: 2
Classifier: Programming Language :: Python :: 2.7
Classifier: Programming Language :: Python :: 3
Classifier: Programming Language :: Python :: 3.4
Classifier: Programming Language :: Python :: 3.5
